CHANGES.rst
CONTRIBUTORS.rst
DEVELOP.rst
LICENSE.GPL
LICENSE.rst
MANIFEST.in
README.rst
requirements.txt
setup.cfg
setup.py
docs/index.rst
src/imio/__init__.py
src/imio.ws.register.egg-info/PKG-INFO
src/imio.ws.register.egg-info/SOURCES.txt
src/imio.ws.register.egg-info/dependency_links.txt
src/imio.ws.register.egg-info/entry_points.txt
src/imio.ws.register.egg-info/namespace_packages.txt
src/imio.ws.register.egg-info/not-zip-safe
src/imio.ws.register.egg-info/requires.txt
src/imio.ws.register.egg-info/top_level.txt
src/imio/ws/__init__.py
src/imio/ws/register/__init__.py
src/imio/ws/register/configure.zcml
src/imio/ws/register/event.py
src/imio/ws/register/testing.py
src/imio/ws/register/tests/__init__.py
src/imio/ws/register/tests/test_event.py