Metadata-Version: 2.1
Name: imio.ws.register
Version: 1.0a4
Summary: Route subscription for webservice routing
Home-page: https://pypi.python.org/pypi/imio.ws.register
Author: Martin Peeters
Author-email: martin.peeters@affinitic.be
License: GPL version 2
Keywords: Python Plone
Platform: UNKNOWN
Classifier: Environment :: Web Environment
Classifier: Framework :: Plone
Classifier: Framework :: Plone :: 4.3
Classifier: Programming Language :: Python
Classifier: Programming Language :: Python :: 2.7
Classifier: Operating System :: OS Independent
Classifier: License :: OSI Approved :: GNU General Public License v2 (GPLv2)
Provides-Extra: test
